{
    "updated": "2026-06-25",
    "scopes": {
        "Global (All)": [
            {
                "title": "",
                "risk_level": "",
                "summary": ""
            },
            {
                "title": "",
                "risk_level": "",
                "summary": ""
            },
            {
                "title": "Russian-Ukrainian Conflict: Escalation Threat",
                "risk_level": "High",
                "summary": "The conflict in Ukraine has entered a new phase, with increased fighting and a rising risk of escalation, which could have significant global implications."
            }
        ],
        "United States": [
            {
                "title": "US Supreme Court Overturns Roe v. Wade, Ending Federal Abortion Rights",
                "risk_level": "High",
                "summary": "The US Supreme Court has overturned Roe v. Wade, ending federal protections for abortion rights. The ruling has sparked widespread protests and concerns about access to reproductive healthcare."
            },
            {
                "title": "Federal Reserve Raises Interest Rates to Combat Inflation",
                "risk_level": "Medium",
                "summary": "The Federal Reserve has raised interest rates to combat inflation, which has been rising due to supply chain disruptions and economic growth."
            },
            {
                "title": "US-China Trade Tensions Escalate Amid Military Build-Up",
                "risk_level": "High",
                "summary": "US-China trade tensions have escalated amid China's military build-up in the South China Sea. The US has expressed concerns about China's expansionist policies in the region."
            }
        ],
        "South Korea": [
            {
                "title": "Protests against COVID-19 response laws in South Korea",
                "risk_level": "Low",
                "summary": "South Korean citizens are protesting the government's new laws, aimed at addressing the pandemic, citing civil liberties concerns."
            },
            {
                "title": "",
                "risk_level": "",
                "summary": ""
            },
            {
                "title": "North Korean ICBM test sparks concern in South Korea",
                "risk_level": "High",
                "summary": "North Korea's test of an intercontinental ballistic missile (ICBM) has raised concerns about regional stability and sparked a response from South Korea."
            }
        ],
        "Japan": [
            {
                "title": "Protests against Japan's new state secrets law",
                "risk_level": "Medium",
                "summary": "Anti-government protesters in Tokyo clashed with police on Friday over the passage of a new state secrets law, which critics say will make it easier for the government to cover up corruption and scandals."
            },
            {
                "title": "Typhoon Mawar hits northern Japan, leaving 2 dead",
                "risk_level": "Medium",
                "summary": "Typhoon Mawar has made landfall in northern Japan, leaving at least two people dead and causing widespread power outages and flooding. The storm is expected to bring heavy rain and strong winds to the region over the next few days."
            },
            {
                "title": "COVID-19 cases rise in Japan as Olympics approach",
                "risk_level": "Low",
                "summary": "Japan has seen a rise in COVID-19 cases in recent days, prompting concerns about the impact on the upcoming Olympics. The government has warned of a potential surge in cases and is urging people to get vaccinated."
            }
        ]
    }
}