{
    "updated": "2026-07-17",
    "scopes": {
        "Global (All)": [
            {
                "title": "Cyberattack on Ukrainian Government Websites",
                "risk_level": "High",
                "summary": "Ukraine has reported a cyberattack on several government websites, prompting concerns about potential data breaches and disruptions to critical services."
            },
            {
                "title": "Increased Tensions Between US and China in South China Sea",
                "risk_level": "High",
                "summary": "The US has reportedly increased its military presence in the South China Sea, raising tensions with China and raising concerns about a potential conflict in the region."
            },
            {
                "title": "Protests in Iran Over Water Shortages and Economic Crisis",
                "risk_level": "High",
                "summary": "Protests have erupted in several cities across Iran over water shortages and economic hardship, highlighting social unrest and potential instability in the country."
            }
        ],
        "United States": [
            {
                "title": "US Border Agents Use Whips on Haitian Refugees",
                "risk_level": "High",
                "summary": "Reports of US border agents using whips against Haitian refugees at the US-Mexico border sparked widespread outrage and calls for action. The incident has raised concerns about human rights abuses and increased scrutiny of the US immigration policy."
            },
            {
                "title": "Texas School Shooting Leaves 21 Dead",
                "risk_level": "High",
                "summary": "A mass shooting at Robb Elementary School in Uvalde, Texas, left 21 people dead, including 19 children. The incident has reignited debates on gun control and school safety in the United States."
            },
            {
                "title": "Supreme Court to Overturn Roe v. Wade",
                "risk_level": "High",
                "summary": "Leaked documents indicate that the US Supreme Court is poised to overturn Roe v. Wade, the landmark 1973 decision that legalized abortion across the United States. The move has sparked concerns about reproductive rights and the impact on women's health."
            }
        ],
        "South Korea": [
            {
                "title": "South Korea Sees Surge in COVID-19 Infections Due to BA.5 Subvariant",
                "risk_level": "Medium",
                "summary": "A sudden surge in COVID-19 cases has been spotted in South Korea due to the BA.5 subvariant. Cases have been increasing rapidly, especially from the last week. The government has recommended taking precautions."
            },
            {
                "title": "",
                "risk_level": "",
                "summary": ""
            },
            {
                "title": "",
                "risk_level": "",
                "summary": ""
            }
        ],
        "Japan": [
            {
                "title": "Typhoon Nanmadol hits eastern Japan, killing 10 and leaving 11 missing",
                "risk_level": "High",
                "summary": "",
                "source": "",
                "date": "",
                "location": "Eastern Japan"
            },
            {
                "title": "Protest against government's security legislation plans escalate in Tokyo",
                "risk_level": "High",
                "summary": "",
                "source": "",
                "date": "",
                "location": "Tokyo"
            },
            {
                "title": "North Korea fires ballistic missile over Japan, prompting alert system",
                "risk_level": "High",
                "summary": "",
                "source": "",
                "date": "",
                "location": "Over Japan"
            }
        ]
    }
}