{
    "updated": "2026-07-17",
    "scopes": {
        "Global (All)": [
            {
                "title": "US-Russia Confrontation Escalates Over Ukraine",
                "risk_level": "High",
                "summary": "The US and Russia have engaged in a tense standoff over Ukraine, with both sides accusing each other of aggressive actions."
            },
            {
                "title": "Global Cyberattack Targets Major Corporations",
                "risk_level": "High",
                "summary": "A widespread cyberattack has targeted several major corporations worldwide, with hackers gaining access to sensitive data and systems."
            },
            {
                "title": "Protests Erupt in Iran Over Economic Austerity Measures",
                "risk_level": "Medium",
                "summary": "Mass protests have broken out in Iran in response to government-imposed economic austerity measures, which have sparked widespread discontent."
            }
        ],
        "United States": [
            {
                "title": "US Supreme Court overturns Roe v. Wade, ending constitutional right to abortion (High)",
                "risk_level": "High",
                "summary": "The US Supreme Court has overturned the landmark Roe v. Wade ruling, effectively ending the constitutional right to abortion. This decision has sparked widespread debate and protests across the country."
            },
            {
                "title": "Gun violence: Multiple school shootings in Florida (Medium)",
                "risk_level": "Medium",
                "summary": "In the past week, multiple school shootings have occurred in Florida, leaving several people injured or dead. This has raised concerns about gun control and school safety."
            },
            {
                "title": "US Immigration: Border Patrol Agents use Whips to detain Migrants (High)",
                "risk_level": "High",
                "summary": "A viral video showing Border Patrol Agents using whips to detain migrants at the US-Mexico border has sparked outrage and accusations of human rights abuses. This incident has raised concerns about the treatment of migrants and refugees."
            }
        ],
        "South Korea": [
            {
                "title": "North Korea Test-Fires Ballistic Missiles",
                "risk_level": "High",
                "summary": "South Korea's Joint Chiefs of Staff reported that North Korea test-fired ballistic missiles off its east coast, prompting a response from the United States and its allies."
            },
            {
                "title": "Seoul to Enhance Cybersecurity Amid Rising Threats",
                "risk_level": "Medium",
                "summary": "South Korea's government announced plans to bolster its cybersecurity capabilities in response to growing threats from state-backed hackers and other malicious actors."
            },
            {
                "title": "Protests Erupt in South Korea Over Economic Reforms",
                "risk_level": "Medium",
                "summary": "Thousands of South Koreans took to the streets to protest proposed economic reforms, which they claim will exacerbate income inequality and hurt the country's working class."
            }
        ],
        "Japan": [
            {
                "title": "Japanese Yen Hits 24-year Low Amid Economic Concerns",
                "risk_level": "High",
                "summary": "The Japanese yen has plummeted to a 24-year low, fueling concerns about the country's economic stability and impacting the global currency market."
            },
            {
                "title": "North Korea Warns Japan Over Military Drills",
                "risk_level": "High",
                "summary": "North Korea has issued a warning to Japan over joint military drills between the US and South Korea, sparking tensions in the region."
            },
            {
                "title": "Japan to Ease COVID-19 Restrictions Despite Rise in Cases",
                "risk_level": "Medium",
                "summary": "Japan's government has decided to ease COVID-19 restrictions, despite a recent surge in cases, in order to boost the country's economy and public activity."
            }
        ]
    }
}